yunbi
