Metadata-Version: 1.0
Name: yunbi
Version: 0.2.1
Summary: A Python wrapper for the yunbi.com api
Home-page: https://github.com/imlonghao/yunbi
Author: imlonghao
Author-email: shield@fastmail.com
License: MIT License
Keywords: Yunbi
Platform: any
